aggfly/__init__.py
aggfly/aggregate/__init__.py
aggfly/aggregate/aggregate.py
aggfly/aggregate/aggregate_utils.py
aggfly/aggregate/spatial.py
aggfly/aggregate/temporal.py
aggfly/aggregate/z_old/spatial-Copy1.py
aggfly/aggregate/z_old/temporal-Copy1.py
aggfly/cache/__init__.py
aggfly/cache/project_cache.py
aggfly/dataset/__init__.py
aggfly/dataset/dataset.py
aggfly/dataset/grid.py
aggfly/dataset/grid_utils.py
aggfly/regions/__init__.py
aggfly/regions/georegions.py
aggfly/regions/shp_utils.py
aggfly/scratch.py
aggfly/tests/__init__.py
aggfly/tests/test_aggregate.py
aggfly/utils.py
aggfly/weights/__init__.py
aggfly/weights/crop_weights.py
aggfly/weights/crop_weights_utils.py
aggfly/weights/grid_weights.py
aggfly/weights/pop_weights.py
aggfly/weights/secondary_weights.py
aggfly-0.1.5.dist-info/LICENSE
aggfly-0.1.5.dist-info/METADATA
aggfly-0.1.5.dist-info/WHEEL
aggfly-0.1.5.dist-info/RECORD
