Metadata-Version: 2.1
Name: aggfly
Version: 0.1.5
Summary: Efficient spatial and temporal aggregation of gridded climate data
Author: Dylan Hogan
Author-email: dth2133@columbia.edu
Requires-Python: >=3.11.6,<3.12.3
Classifier: Programming Language :: Python :: 3
Classifier: Programming Language :: Python :: 3.12
Requires-Dist: dask (>=2023.11.0,<2024.0.0)
Requires-Dist: dask-geopandas (>=0.3.1,<0.4.0)
Requires-Dist: dill (>=0.3.8,<0.4.0)
Requires-Dist: geopandas (>=0.14.4,<0.15.0)
Requires-Dist: matplotlib (>=3.9.0,<4.0.0)
Requires-Dist: netcdf4 (>=1.6.5,<2.0.0)
Requires-Dist: numba (>=0.59.1,<0.60.0)
Requires-Dist: numpy (>=1.26.4,<2.0.0)
Requires-Dist: pandas (>=2.2.2,<3.0.0)
Requires-Dist: pyarrow (>=16.1.0,<17.0.0)
Requires-Dist: pytest (>=8.2.1,<9.0.0)
Requires-Dist: pyyaml (>=6.0.1,<7.0.0)
Requires-Dist: rasterio (>=1.3.10,<2.0.0)
Requires-Dist: rioxarray (>=0.15.5,<0.16.0)
Requires-Dist: shapely (>=2.0.4,<3.0.0)
Requires-Dist: xarray (>=2024.5.0,<2025.0.0)
Requires-Dist: zarr (>=2.18.2,<3.0.0)
